highcharts_gantt/__init__.py
highcharts_gantt/__version__.py
highcharts_gantt/ai.py
highcharts_gantt/chart.py
highcharts_gantt/constants.py
highcharts_gantt/decorators.py
highcharts_gantt/errors.py
highcharts_gantt/headless_export.py
highcharts_gantt/highcharts.py
highcharts_gantt/js_literal_functions.py
highcharts_gantt/metaclasses.py
highcharts_gantt/monday.py
highcharts_gantt/utility_functions.py
highcharts_gantt/global_options/__init__.py
highcharts_gantt/global_options/shared_options.py
highcharts_gantt/global_options/language/__init__.py
highcharts_gantt/global_options/language/export_data.py
highcharts_gantt/global_options/language/navigation.py
highcharts_gantt/global_options/language/stock_tools.py
highcharts_gantt/global_options/language/accessibility/__init__.py
highcharts_gantt/global_options/language/accessibility/announce_new_data.py
highcharts_gantt/global_options/language/accessibility/axis.py
highcharts_gantt/global_options/language/accessibility/chart_types.py
highcharts_gantt/global_options/language/accessibility/exporting.py
highcharts_gantt/global_options/language/accessibility/legend.py
highcharts_gantt/global_options/language/accessibility/navigator.py
highcharts_gantt/global_options/language/accessibility/range_selector.py
highcharts_gantt/global_options/language/accessibility/screen_reader_section.py
highcharts_gantt/global_options/language/accessibility/series.py
highcharts_gantt/global_options/language/accessibility/sonification.py
highcharts_gantt/global_options/language/accessibility/table.py
highcharts_gantt/global_options/language/accessibility/zoom.py
highcharts_gantt/options/__init__.py
highcharts_gantt/options/boost.py
highcharts_gantt/options/caption.py
highcharts_gantt/options/connectors.py
highcharts_gantt/options/credits.py
highcharts_gantt/options/data.py
highcharts_gantt/options/defs.py
highcharts_gantt/options/drilldown.py
highcharts_gantt/options/loading.py
highcharts_gantt/options/navigator.py
highcharts_gantt-1.7.0.dist-info/METADATA
highcharts_gantt-1.7.0.dist-info/WHEEL
highcharts_gantt-1.7.0.dist-info/licenses/LICENSE
highcharts_gantt-1.7.0.dist-info/RECORD
